<PAMDataset>
  <PAMRasterBand band="1">
    <Metadata>
      <MDI key="STATISTICS_MAXIMUM">219</MDI>
      <MDI key="STATISTICS_MEAN">104.09637451172</MDI>
      <MDI key="STATISTICS_MINIMUM">0</MDI>
      <MDI key="STATISTICS_STDDEV">46.915098295085</MDI>
      <MDI key="STATISTICS_VALID_PERCENT">100</MDI>
    </Metadata>
  </PAMRasterBand>
  <PAMRasterBand band="2">
    <Metadata>
      <MDI key="STATISTICS_MAXIMUM">193</MDI>
      <MDI key="STATISTICS_MEAN">102.73002624512</MDI>
      <MDI key="STATISTICS_MINIMUM">21</MDI>
      <MDI key="STATISTICS_STDDEV">31.927025641994</MDI>
      <MDI key="STATISTICS_VALID_PERCENT">100</MDI>
    </Metadata>
  </PAMRasterBand>
  <PAMRasterBand band="3">
    <Metadata>
      <MDI key="STATISTICS_MAXIMUM">169</MDI>
      <MDI key="STATISTICS_MEAN">72.138732910156</MDI>
      <MDI key="STATISTICS_MINIMUM">0</MDI>
      <MDI key="STATISTICS_STDDEV">29.845745658994</MDI>
      <MDI key="STATISTICS_VALID_PERCENT">100</MDI>
    </Metadata>
  </PAMRasterBand>
</PAMDataset>
